Frequency Divider/PES_freqdiv.v
module PES_freqdiv(en,clkin,n,clkout);

input clkin;
input [3:0]n;
input en;
reg [3:0]pc;
reg [3:0]nc;
output clkout;

always@(posedge clkin)
begin
if(en==1)
begin
  if(pc<(n-1))
	pc<=pc+1;
  else
	pc<=0;
end
else
 pc<=0;
end

always@(negedge clkin)
begin
if(en==1)
begin
  if(nc<(n-1))
	nc<=nc+1;
  else
	nc<=0;
end
else
  nc<=0;
end

assign clkout=(n%2==0)?(pc<n/2):((pc<(n/2)+1)&&(nc<(n/2)+1));
endmodule

Frequency Divider/PES_freqdiv_tb.v
`timescale 1ns/1ps
module PES_freqdiv_tb;

reg clk;
reg en;
reg [3:0]n;
wire clkout;

PES_freqdiv f1(en,clk,n,clkout);

initial
begin
clk=0;
en=0;
n=3;
$dumpfile ("PES_freqdiv_vcd.vcd"); 
$dumpvars(0,PES_freqdiv_tb);


forever
#10 clk=~clk;

end


initial
begin
#40 en=1;
#340 n=4; 
#440 n=11;
#1100 n=6;
#640 $finish;

end 
endmodule

Frequency Divider/PES_freqdiv_vcd.vcd
$date
	Mon Oct 23 22:21:04 2023
$end
$version
	Icarus Verilog
$end
$timescale
	1ps
$end
$scope module PES_freqdiv_tb $end
$var wire 1 ! clkout $end
$var reg 1 " clk $end
$var reg 1 # en $end
$var reg 4 $ n [3:0] $end
$scope module f1 $end
$var wire 1 " clkin $end
$var wire 1 # en $end
$var wire 4 % n [3:0] $end
$var wire 1 ! clkout $end
$var reg 4 & nc [3:0] $end
$var reg 4 ' pc [3:0] $end
$upscope $end
$upscope $end
$enddefinitions $end
#0
$dumpvars
bx '
b0 &
b11 %
b11 $
0#
0"
x!
$end
#10000
1!
b0 '
1"
#20000
0"
#30000
1"
#40000
b1 &
0"
1#
#50000
b1 '
1"
#60000
0!
b10 &
0"
#70000
b10 '
1"
#80000
b0 &
0"
#90000
1!
b0 '
1"
#100000
b1 &
0"
#110000
b1 '
1"
#120000
0!
b10 &
0"
#130000
b10 '
1"
#140000
b0 &
0"
#150000
1!
b0 '
1"
#160000
b1 &
0"
#170000
b1 '
1"
#180000
0!
b10 &
0"
#190000
b10 '
1"
#200000
b0 &
0"
#210000
1!
b0 '
1"
#220000
b1 &
0"
#230000
b1 '
1"
#240000
0!
b10 &
0"
#250000
b10 '
1"
#260000
b0 &
0"
#270000
1!
b0 '
1"
#280000
b1 &
0"
#290000
b1 '
1"
#300000
0!
b10 &
0"
#310000
b10 '
1"
#320000
b0 &
0"
#330000
1!
b0 '
1"
#340000
b1 &
0"
#350000
b1 '
1"
#360000
0!
b10 &
0"
#370000
b10 '
1"
#380000
b11 &
0"
b100 $
b100 %
#390000
b11 '
1"
#400000
b0 &
0"
#410000
1!
b0 '
1"
#420000
b1 &
0"
#430000
b1 '
1"
#440000
b10 &
0"
#450000
0!
b10 '
1"
#460000
b11 &
0"
#470000
b11 '
1"
#480000
b0 &
0"
#490000
1!
b0 '
1"
#500000
b1 &
0"
#510000
b1 '
1"
#520000
b10 &
0"
#530000
0!
b10 '
1"
#540000
b11 &
0"
#550000
b11 '
1"
#560000
b0 &
0"
#570000
1!
b0 '
1"
#580000
b1 &
0"
#590000
b1 '
1"
#600000
b10 &
0"
#610000
0!
b10 '
1"
#620000
b11 &
0"
#630000
b11 '
1"
#640000
b0 &
0"
#650000
1!
b0 '
1"
#660000
b1 &
0"
#670000
b1 '
1"
#680000
b10 &
0"
#690000
0!
b10 '
1"
#700000
b11 &
0"
#710000
b11 '
1"
#720000
b0 &
0"
#730000
1!
b0 '
1"
#740000
b1 &
0"
#750000
b1 '
1"
#760000
b10 &
0"
#770000
0!
b10 '
1"
#780000
b11 &
0"
#790000
b11 '
1"
#800000
b0 &
0"
#810000
1!
b0 '
1"
#820000
b1 &
0"
b1011 $
b1011 %
#830000
b1 '
1"
#840000
b10 &
0"
#850000
b10 '
1"
#860000
b11 &
0"
#870000
b11 '
1"
#880000
b100 &
0"
#890000
b100 '
1"
#900000
b101 &
0"
#910000
b101 '
1"
#920000
0!
b110 &
0"
#930000
b110 '
1"
#940000
b111 &
0"
#950000
b111 '
1"
#960000
b1000 &
0"
#970000
b1000 '
1"
#980000
b1001 &
0"
#990000
b1001 '
1"
#1000000
b1010 &
0"
#1010000
b1010 '
1"
#1020000
b0 &
0"
#1030000
1!
b0 '
1"
#1040000
b1 &
0"
#1050000
b1 '
1"
#1060000
b10 &
0"
#1070000
b10 '
1"
#1080000
b11 &
0"
#1090000
b11 '
1"
#1100000
b100 &
0"
#1110000
b100 '
1"
#1120000
b101 &
0"
#1130000
b101 '
1"
#1140000
0!
b110 &
0"
#1150000
b110 '
1"
#1160000
b111 &
0"
#1170000
b111 '
1"
#1180000
b1000 &
0"
#1190000
b1000 '
1"
#1200000
b1001 &
0"
#1210000
b1001 '
1"
#1220000
b1010 &
0"
#1230000
b1010 '
1"
#1240000
b0 &
0"
#1250000
1!
b0 '
1"
#1260000
b1 &
0"
#1270000
b1 '
1"
#1280000
b10 &
0"
#1290000
b10 '
1"
#1300000
b11 &
0"
#1310000
b11 '
1"
#1320000
b100 &
0"
#1330000
b100 '
1"
#1340000
b101 &
0"
#1350000
b101 '
1"
#1360000
0!
b110 &
0"
#1370000
b110 '
1"
#1380000
b111 &
0"
#1390000
b111 '
1"
#1400000
b1000 &
0"
#1410000
b1000 '
1"
#1420000
b1001 &
0"
#1430000
b1001 '
1"
#1440000
b1010 &
0"
#1450000
b1010 '
1"
#1460000
b0 &
0"
#1470000
1!
b0 '
1"
#1480000
b1 &
0"
#1490000
b1 '
1"
#1500000
b10 &
0"
#1510000
b10 '
1"
#1520000
b11 &
0"
#1530000
b11 '
1"
#1540000
b100 &
0"
#1550000
b100 '
1"
#1560000
b101 &
0"
#1570000
b101 '
1"
#1580000
0!
b110 &
0"
#1590000
b110 '
1"
#1600000
b111 &
0"
#1610000
b111 '
1"
#1620000
b1000 &
0"
#1630000
b1000 '
1"
#1640000
b1001 &
0"
#1650000
b1001 '
1"
#1660000
b1010 &
0"
#1670000
b1010 '
1"
#1680000
b0 &
0"
#1690000
1!
b0 '
1"
#1700000
b1 &
0"
#1710000
b1 '
1"
#1720000
b10 &
0"
#1730000
b10 '
1"
#1740000
b11 &
0"
#1750000
b11 '
1"
#1760000
b100 &
0"
#1770000
b100 '
1"
#1780000
b101 &
0"
#1790000
b101 '
1"
#1800000
0!
b110 &
0"
#1810000
b110 '
1"
#1820000
b111 &
0"
#1830000
b111 '
1"
#1840000
b1000 &
0"
#1850000
b1000 '
1"
#1860000
b1001 &
0"
#1870000
b1001 '
1"
#1880000
b1010 &
0"
#1890000
b1010 '
1"
#1900000
b0 &
0"
#1910000
1!
b0 '
1"
#1920000
b1 &
0"
b110 $
b110 %
#1930000
b1 '
1"
#1940000
b10 &
0"
#1950000
b10 '
1"
#1960000
b11 &
0"
#1970000
0!
b11 '
1"
#1980000
b100 &
0"
#1990000
b100 '
1"
#2000000
b101 &
0"
#2010000
b101 '
1"
#2020000
b0 &
0"
#2030000
1!
b0 '
1"
#2040000
b1 &
0"
#2050000
b1 '
1"
#2060000
b10 &
0"
#2070000
b10 '
1"
#2080000
b11 &
0"
#2090000
0!
b11 '
1"
#2100000
b100 &
0"
#2110000
b100 '
1"
#2120000
b101 &
0"
#2130000
b101 '
1"
#2140000
b0 &
0"
#2150000
1!
b0 '
1"
#2160000
b1 &
0"
#2170000
b1 '
1"
#2180000
b10 &
0"
#2190000
b10 '
1"
#2200000
b11 &
0"
#2210000
0!
b11 '
1"
#2220000
b100 &
0"
#2230000
b100 '
1"
#2240000
b101 &
0"
#2250000
b101 '
1"
#2260000
b0 &
0"
#2270000
1!
b0 '
1"
#2280000
b1 &
0"
#2290000
b1 '
1"
#2300000
b10 &
0"
#2310000
b10 '
1"
#2320000
b11 &
0"
#2330000
0!
b11 '
1"
#2340000
b100 &
0"
#2350000
b100 '
1"
#2360000
b101 &
0"
#2370000
b101 '
1"
#2380000
b0 &
0"
#2390000
1!
b0 '
1"
#2400000
b1 &
0"
#2410000
b1 '
1"
#2420000
b10 &
0"
#2430000
b10 '
1"
#2440000
b11 &
0"
#2450000
0!
b11 '
1"
#2460000
b100 &
0"
#2470000
b100 '
1"
#2480000
b101 &
0"
#2490000
b101 '
1"
#2500000
b0 &
0"
#2510000
1!
b0 '
1"
#2520000
b1 &
0"
#2530000
b1 '
1"
#2540000
b10 &
0"
#2550000
b10 '
1"
#2560000
b11 &
0"
